pdns/__init__.py
pdns/remotebackend/__init__.py
pdns/remotebackend/unix.py
Pdns_Remotebackend-0.8.1.dist-info/LICENSE
Pdns_Remotebackend-0.8.1.dist-info/METADATA
Pdns_Remotebackend-0.8.1.dist-info/WHEEL
Pdns_Remotebackend-0.8.1.dist-info/top_level.txt
Pdns_Remotebackend-0.8.1.dist-info/RECORD
