Metadata-Version: 2.1
Name: Pdns_Remotebackend
Version: 0.8.1
Summary: Support package for PowerDNS remotebackend
Home-page: https://github.com/cmouse/pdns-remotebackend-python
Download-URL: https://pypi.org/project/Pdns_Remotebackend
Author: Aki Tuomi
Author-email: cmouse@cmouse.fi
License: MIT
Platform: all
Classifier: Development Status :: 4 - Beta
Classifier: Intended Audience :: Developers
Classifier: Intended Audience :: System Administrators
Classifier: License :: OSI Approved :: MIT License
Classifier: Operating System :: OS Independent
Classifier: Programming Language :: Python
Classifier: Topic :: Internet :: Name Service (DNS)
License-File: LICENSE
